alu.sv
module alu(input[31:0] alu_op1, input[31:0] alu_op2, input [2:0] alu_control, output [31:0] alu_out);
    always_comb begin
        case(alu_control)
            3'd0: alu_out = alu_op1 + alu_op2;
            3'd1: alu_out = alu_op1 - alu_op2; //verify polarity against instruction!
            3'd2: alu_out = alu_op1 & alu_op2;
            3'd3: alu_out = alu_op1 | alu_op2;
            // 3'd4:;
            3'd5: alu_out = {31'b0, {alu_op1 < alu_op2}};
            // 3'd6:;
            // 3'd7:;  
            default: alu_out = 32'b0;
        endcase
    end
endmodule

alu.vcd
$version Generated by VerilatedVcd $end
$timescale 1ps $end
 $scope module TOP $end
  $var wire 32 " alu_op1 [31:0] $end
  $var wire 32 # alu_op2 [31:0] $end
  $var wire 3 $ alu_control [2:0] $end
  $var wire 32 % alu_out [31:0] $end
  $scope module alu $end
   $var wire 32 " alu_op1 [31:0] $end
   $var wire 32 # alu_op2 [31:0] $end
   $var wire 3 $ alu_control [2:0] $end
   $var wire 32 % alu_out [31:0] $end
  $upscope $end
 $upscope $end
$enddefinitions $end


#0
b11111111111111111111111111110101 "
b11111111111111111111111111110010 #
b101 $
b00000000000000000000000000000000 %
#1
b11111111111111111111111111110011 #
#2
b11111111111111111111111111110100 #
#3
b11111111111111111111111111110101 #
#4
b11111111111111111111111111110110 #
b00000000000000000000000000000001 %
#5
b11111111111111111111111111110111 #
#6
b11111111111111111111111111111000 #
#7
b11111111111111111111111111111001 #
#8
b11111111111111111111111111111010 #
#9
b11111111111111111111111111111011 #
#10
b11111111111111111111111111111100 #
#11
b11111111111111111111111111111101 #
#12
b11111111111111111111111111111110 #
#13
b11111111111111111111111111111111 #
#14
b00000000000000000000000000000000 #
b00000000000000000000000000000000 %
#15
b00000000000000000000000000000001 #
#16
b00000000000000000000000000000010 #
#17
b00000000000000000000000000000011 #
#18
b00000000000000000000000000000100 #
#19
b00000000000000000000000000000101 #
#20
b00000000000000000000000000000110 #
#21
b00000000000000000000000000000111 #
#22
b00000000000000000000000000001000 #
#23
b00000000000000000000000000001001 #
#24
b00000000000000000000000000001010 #
#25
b00000000000000000000000000001011 "
b11111111111111111111111111110111 #
b00000000000000000000000000000001 %
#26
b11111111111111111111111111111000 #
#27
b11111111111111111111111111111001 #
#28
b11111111111111111111111111111010 #
#29
b11111111111111111111111111111011 #
#30
b11111111111111111111111111111100 #
#31
b11111111111111111111111111111101 #
#32
b11111111111111111111111111111110 #
#33
b11111111111111111111111111111111 #
#34
b00000000000000000000000000000000 #
b00000000000000000000000000000000 %
#35
b00000000000000000000000000000001 #
#36
b00000000000000000000000000000010 #
#37
b00000000000000000000000000000011 #
#38
b00000000000000000000000000000100 #
#39
b00000000000000000000000000000101 #
#40
b00000000000000000000000000000110 #
#41
b00000000000000000000000000000111 #
#42
b00000000000000000000000000001000 #
#43
b00000000000000000000000000001001 #
#44
b00000000000000000000000000001010 #
#45
b00000000000000000000000000001011 #
#46
b00000000000000000000000000001100 #
b00000000000000000000000000000001 %
#47
b00000000000000000000000000001101 #
#48
b00000000000000000000000000001110 #
#49
b00000000000000000000000000001111 #
